{"http_method":"GET","revision":"8e6688b0b7753b24a96be7764d3721bd","results":{"access_group":"wanoptgrp","category":"complex","children":{"local-cache-id":{"category":"unitary","default":"","help":"ID that this device uses to connect to the remote device.","multiple_values":false,"name":"local-cache-id","size":35,"type":"string"},"remote-cache-id":{"category":"unitary","default":"","help":"ID of the remote device to which the device connects.","multiple_values":false,"name":"remote-cache-id","size":35,"type":"string"},"remote-cache-ip":{"category":"unitary","default":"0.0.0.0","help":"IP address of the remote device to which the device connects.","multiple_values":false,"name":"remote-cache-ip","type":"ipv4-address-any"},"status":{"category":"unitary","default":"disable","help":"Enable/disable using remote device as Web cache storage.","multiple_values":false,"name":"status","options":[{"help":"Use local disks as Web cache storage.","name":"disable"},{"help":"Use a remote device as Web cache storage.","name":"enable"}],"type":"option"}},"help":"Configure a remote cache device as Web cache storage.","multiple_values":false,"name":"remote-storage","path":"wanopt","q_type":341},"vdom":"root","path":"wanopt","name":"remote-storage","status":"success","http_status":200,"serial":"FGTAZRBTDHDQ0I17","version":"v7.0.5","build":304}