{"http_method":"GET","revision":"8e6688b0b7753b24a96be7764d3721bd","results":{"access_group":"wifi","category":"table","children":{"nai-list":{"category":"table","children":{"name":{"category":"unitary","default":"","help":"OSU NAI ID.","multiple_values":false,"name":"name","size":35,"type":"string"},"osu-nai":{"category":"unitary","default":"","help":"OSU NAI.","multiple_values":false,"name":"osu-nai","required":true,"size":255,"type":"string"}},"help":"OSU NAI list.","max_table_size_global":0,"max_table_size_item":0,"max_table_size_vdom":3,"mkey":"name","mkey_type":"string","name":"nai-list"},"name":{"category":"unitary","default":"","help":"OSU provider NAI ID.","multiple_values":false,"name":"name","size":35,"type":"string"}},"help":"Configure online sign up (OSU) provider NAI list.","max_table_size_global":0,"max_table_size_item":0,"max_table_size_vdom":16,"mkey":"name","mkey_type":"string","name":"h2qp-osu-provider-nai","path":"wireless-controller.hotspot20","q_type":297},"vdom":"root","path":"wireless-controller.hotspot20","name":"h2qp-osu-provider-nai","status":"success","http_status":200,"serial":"FGTAZRBTDHDQ0I17","version":"v7.0.5","build":304}