{"http_method":"GET","revision":"f4f320db1b69e5bbd863b8252c73140d","results":{"access_group":"fwgrp","category":"table","children":{"id":{"category":"unitary","default":0,"help":"IP block list reason ID.","max-value":4294967295,"min-value":0,"multiple_values":false,"name":"id","type":"integer"},"name":{"category":"unitary","default":"","help":"IP block list reason name.","multiple_values":false,"name":"name","size":63,"type":"string"}},"help":"IP block list reason.","max_table_size_global":0,"max_table_size_item":0,"max_table_size_vdom":0,"mkey":"id","mkey_type":"integer","name":"internet-service-ipbl-reason","object_range":"global","path":"firewall","q_type":354,"readonly":true},"vdom":"root","path":"firewall","name":"internet-service-ipbl-reason","status":"success","http_status":200,"serial":"FG180FTK20900788","version":"v7.2.8","build":1639}